MANIFEST.in
README.rst
setup.py
django_webfaction.egg-info/PKG-INFO
django_webfaction.egg-info/SOURCES.txt
django_webfaction.egg-info/dependency_links.txt
django_webfaction.egg-info/entry_points.txt
django_webfaction.egg-info/requires.txt
django_webfaction.egg-info/top_level.txt
webfaction/__init__.py
webfaction/api.py
webfaction/backends.py
webfaction/middleware.py