Metadata-Version: 1.0
Name: django-webfaction
Version: 2.0
Summary: Collection of tools to run django on webfaction more seamless
Home-page: http://bitbucket.org/zeus/django-webfaction/
Author: Pavel Zhukov
Author-email: gelios@gmail.com
License: GPL
Keywords: webfaction,django
Platform: UNKNOWN
